{
    "sections": [
        {
            "title": "Home",
            "href": "/"
        },
        {
            "title": "About",
            "href": "/about"
        },
        {
            "title": "Skills",
            "href": "/skills"
        },
        {
            "title": "Education",
            "href": "/education"
        },
        {
            "title": "Experience",
            "href": "/experience"
        },
        {
            "title": "Projects",
            "href": "/projects"
        },
        {
            "title": "Resume",
            "href": "https://drive.google.com/file/d/13zTeP9y1YqeJte_oeJnXk4L50-M1Zuxy/view?usp=sharing",
            "type": "link"
        }
    ]

}
